langchain_soniox/__init__.py
langchain_soniox/document_loaders.py
langchain_soniox/errors.py
langchain_soniox/types.py
langchain_soniox-0.1.0.dist-info/METADATA
langchain_soniox-0.1.0.dist-info/WHEEL
langchain_soniox-0.1.0.dist-info/licenses/LICENSE
langchain_soniox-0.1.0.dist-info/RECORD
