Metadata-Version: 2.4
Name: langchain-soniox
Version: 0.1.0
Summary: LangChain integration for Soniox
Project-URL: Homepage, https://soniox.com/
Project-URL: Repository, https://github.com/soniox/langchain-soniox
Author-email: Soniox Inc <support@soniox.com>
License: MIT
License-File: LICENSE
Classifier: License :: OSI Approved :: MIT License
Classifier: Operating System :: OS Independent
Classifier: Programming Language :: Python :: 3
Requires-Python: >=3.9
Requires-Dist: httpx>=0.27.0
Requires-Dist: langchain-core>=0.3.0
Provides-Extra: dev
Requires-Dist: mypy>=1.0.0; extra == 'dev'
Requires-Dist: pytest-asyncio>=1.2.0; extra == 'dev'
Requires-Dist: pytest>=8.4.2; extra == 'dev'
Requires-Dist: ruff>=0.9.0; extra == 'dev'
